PyVirtuinLogging-0.10.3.dist-info/METADATA
PyVirtuinLogging-0.10.3.dist-info/RECORD
PyVirtuinLogging-0.10.3.dist-info/WHEEL
PyVirtuinLogging-0.10.3.dist-info/top_level.txt
PyVirtuinLogging-0.10.3.dist-info/zip-safe
pyvirtuinlogging/__init__.py
pyvirtuinlogging/virtuinlogger.py
